{
    "271394014358405121": {
        "name": "Pollux",
        "modules": {
            "PERMS": 0,
            "level": 0,
            "exp": 0,
            "goodies": 626,
            "coins": 0,
            "medals": {},
            "expenses": {
                "putaria": 0,
                "jogatina": 200,
                "drops": 0,
                "trade": 0
            },
            "earnings": {
                "putaria": 5,
                "jogatina": 0,
                "drops": 0,
                "trade": 0
            },
            "dyStreak": 8,
            "daily": 1486595162497,
            "persotext": ""
        }
    },
    "131183400680685568": {
        "name": "JustSumGuy",
        "modules": {
            "PERMS": 3,
            "level": 0,
            "exp": 1,
            "goodies": 698,
            "coins": 0,
            "medals": {},
            "expenses": {
                "putaria": 0,
                "jogatina": 0,
                "drops": 0,
                "trade": 0
            },
            "earnings": {
                "putaria": 0,
                "jogatina": 0,
                "drops": 0,
                "trade": 0
            },
            "dyStreak": 8,
            "daily": 1486595162497,
            "persotext": ""
        }
    },
    "88120564400553984": {
        "name": "Flicky",
        "modules": {
            "PERMS": 0,
            "level": 0,
            "exp": 26,
            "goodies": 715,
            "coins": 0,
            "medals": {},
            "expenses": {
                "putaria": 5,
                "jogatina": 100,
                "drops": 0,
                "trade": 0
            },
            "earnings": {
                "putaria": 0,
                "jogatina": 200,
                "drops": 0,
                "trade": 0
            },
            "dyStreak": 8,
            "daily": 1486595162497,
            "persotext": ""
        }
    },
    "132581875536494592": {
        "name": "DrCelt",
        "modules": {
            "PERMS": 3,
            "level": 0,
            "exp": 4,
            "goodies": 661,
            "coins": 0,
            "medals": {},
            "expenses": {
                "putaria": 0,
                "jogatina": 0,
                "drops": 0,
                "trade": 0
            },
            "earnings": {
                "putaria": 0,
                "jogatina": 0,
                "drops": 0,
                "trade": 0
            },
            "dyStreak": 8,
            "daily": 1486595162497,
            "persotext": ""
        }
    },
    "85389411201601536": {
        "name": "Zealot",
        "modules": {
            "PERMS": 3,
            "level": 0,
            "exp": 5,
            "goodies": 634,
            "coins": 0,
            "medals": {},
            "expenses": {
                "putaria": 0,
                "jogatina": 0,
                "drops": 0,
                "trade": 0
            },
            "earnings": {
                "putaria": 0,
                "jogatina": 0,
                "drops": 0,
                "trade": 0
            },
            "dyStreak": 8,
            "daily": 1486595162497,
            "persotext": ""
        }
    },
    "160872652108595200": {
        "name": "kolith",
        "modules": {
            "PERMS": 3,
            "level": 1,
            "exp": 45,
            "goodies": 623,
            "coins": 0,
            "medals": {},
            "expenses": {
                "putaria": 0,
                "jogatina": 0,
                "drops": 0,
                "trade": 0
            },
            "earnings": {
                "putaria": 0,
                "jogatina": 0,
                "drops": 0,
                "trade": 0
            },
            "dyStreak": 8,
            "daily": 1486595162497,
            "persotext": ""
        }
    },
    "109175018570661888": {
        "name": "carshalash",
        "modules": {
            "PERMS": 3,
            "level": 0,
            "exp": 3,
            "goodies": 667,
            "coins": 0,
            "medals": {},
            "expenses": {
                "putaria": 0,
                "jogatina": 0,
                "drops": 0,
                "trade": 0
            },
            "earnings": {
                "putaria": 0,
                "jogatina": 0,
                "drops": 0,
                "trade": 0
            },
            "dyStreak": 8,
            "daily": 1486595162497,
            "persotext": ""
        }
    },
    "182311436259819520": {
        "name": "cptwad",
        "modules": {
            "PERMS": 3,
            "level": 0,
            "exp": 2,
            "goodies": 679,
            "coins": 0,
            "medals": {},
            "expenses": {
                "putaria": 0,
                "jogatina": 0,
                "drops": 0,
                "trade": 0
            },
            "earnings": {
                "putaria": 0,
                "jogatina": 0,
                "drops": 0,
                "trade": 0
            },
            "dyStreak": 8,
            "daily": 1486595162497,
            "persotext": ""
        }
    },
    "146851769857605632": {
        "name": "ChocolateMoose",
        "modules": {
            "PERMS": 3,
            "level": 0,
            "exp": 4,
            "goodies": 700,
            "coins": 0,
            "medals": {},
            "expenses": {
                "putaria": 0,
                "jogatina": 0,
                "drops": 0,
                "trade": 0
            },
            "earnings": {
                "putaria": 0,
                "jogatina": 0,
                "drops": 0,
                "trade": 0
            },
            "dyStreak": 8,
            "daily": 1486595162497,
            "persotext": ""
        }
    },
    "162480696298831872": {
        "name": "Leon",
        "modules": {
            "PERMS": 3,
            "level": 0,
            "exp": 4,
            "goodies": 663,
            "coins": 0,
            "medals": {},
            "expenses": {
                "putaria": 0,
                "jogatina": 0,
                "drops": 0,
                "trade": 0
            },
            "earnings": {
                "putaria": 0,
                "jogatina": 0,
                "drops": 0,
                "trade": 0
            },
            "dyStreak": 8,
            "daily": 1486595162497,
            "persotext": ""
        }
    },
    "101535302354505728": {
        "name": "Connoisoisoi",
        "modules": {
            "PERMS": 3,
            "level": 0,
            "exp": 1,
            "goodies": 617,
            "coins": 0,
            "medals": {},
            "expenses": {
                "putaria": 0,
                "jogatina": 0,
                "drops": 0,
                "trade": 0
            },
            "earnings": {
                "putaria": 0,
                "jogatina": 0,
                "drops": 0,
                "trade": 0
            },
            "dyStreak": 8,
            "daily": 1486595162497,
            "persotext": ""
        }
    },
    "155051241028714497": {
        "name": "Quiznip",
        "modules": {
            "PERMS": 0,
            "level": 0,
            "exp": 14,
            "goodies": 681,
            "coins": 0,
            "medals": {},
            "expenses": {
                "putaria": 0,
                "jogatina": 0,
                "drops": 0,
                "trade": 0
            },
            "earnings": {
                "putaria": 0,
                "jogatina": 0,
                "drops": 0,
                "trade": 0
            },
            "dyStreak": 8,
            "daily": 1486595162497,
            "persotext": ""
        }
    },
    "271810114975956995": {
        "name": "Kicock",
        "modules": {
            "PERMS": 3,
            "level": 0,
            "exp": 5,
            "goodies": 648,
            "coins": 0,
            "medals": {},
            "expenses": {
                "putaria": 0,
                "jogatina": 0,
                "drops": 0,
                "trade": 0
            },
            "earnings": {
                "putaria": 0,
                "jogatina": 0,
                "drops": 0,
                "trade": 0
            },
            "dyStreak": 8,
            "daily": 1486595162497,
            "persotext": ""
        }
    }
}
